PyNAU7802/NAU7802.py
PyNAU7802/__init__.py
PyNAU7802-0.2.1.dist-info/LICENSE
PyNAU7802-0.2.1.dist-info/METADATA
PyNAU7802-0.2.1.dist-info/WHEEL
PyNAU7802-0.2.1.dist-info/top_level.txt
PyNAU7802-0.2.1.dist-info/RECORD
