Metadata-Version: 2.1
Name: PyNAU7802
Version: 0.2.1
Summary: Python port of the SparkFun Qwiic Scale NAU7802 Arduino Library
Home-page: https://github.com/BrunoB81HK/PyNAU7802.git
Author: Bruno-Pier Busque
Author-email: bruno-pier.busque@usherbrooke.ca
License: UNKNOWN
Platform: UNKNOWN
Classifier: Programming Language :: Python :: 3
Classifier: License :: OSI Approved :: MIT License
License-File: LICENSE
Requires-Dist: smbus2 (>=0.3)
